{"sidebar":{"search-3":{"title":"Search Blog"},"categories-3":{"title":"Categories","count":0,"hierarchical":0,"dropdown":0},"archives-3":{"title":"Blog Archives","count":0,"dropdown":1},"tag_cloud-1":{"title":"Blog Tags","taxonomy":"post_tag"},"latest_posts-1":{"title":"POPULAR POSTS","count_posts":"3"}},"footer-sidebar":{"info_widget-1":{"title":"The <strong>San<i> Jose<\/i><\/strong> Startup","form_text":"The world's leading prototyping, collaboration & workflow platform.","image":"","url_tw":"#","url_fb":"#","url_gg":"#","url_pt":"#","url_lk":"#"},"nav_menu-1":{"title":"Home","nav_menu":45},"nav_menu-2":{"title":"Page","nav_menu":46}}}